{
    "Name": "STEPHEN SINGER",
    "Profession": "DEVELOPER | DESIGNER | WRITER",
    "Message": "Hello there! I'm currently an Electronics Engineering student at the University of the Philippines Diliman, developing my writing, designing, and programming skills. I'm the eldest of three in my family, currently living in Tondo, Manila. Driven to learn and improve myself, I do my work with diligence.",
    "GithubLink": "https://github.com/Ayumu098",
    "FacebookLink": "https://www.facebook.com/stephen.s.singer"
}